{
  "d" : {
    "results" : [
      {
        "__metadata" : {
          "id" : "https://DEVSAPHRAPP01.ips.gov.il:4300/sap/opu/odata/sap/Z_PRESENCE_SRV/GetReasonsSet('00102236')",
          "uri" : "https://DEVSAPHRAPP01.ips.gov.il:4300/sap/opu/odata/sap/Z_PRESENCE_SRV/GetReasonsSet('00102236')",
          "type" : "Z_PRESENCE_SRV.GetReasons"
        },
        "ReportHours" : false,
        "IvCaller" : "",
        "ReportFullDays" : true,
        "IvUserName" : "",
        "CompleteDay" : true,
        "IvPersonnelNumber" : "00000000",
        "IvDate" : null,
        "IvPossiblePeriodReport" : "",
        "Pernr" : "00102236",
        "Date" : "\/Date(1779148800000)\/",
        "Code" : "0100",
        "TextCode" : "חופשה",
        "TimeInfty" : "2001",
        "PeriodReport" : true,
        "ManagerApprove" : false,
        "AdministratorApprove" : false,
        "AddFile" : false,
        "ReportComment" : false,
        "AdditionalAbsenceData" : false
      },
      {
        "__metadata" : {
          "id" : "https://DEVSAPHRAPP01.ips.gov.il:4300/sap/opu/odata/sap/Z_PRESENCE_SRV/GetReasonsSet('00102236')",
          "uri" : "https://DEVSAPHRAPP01.ips.gov.il:4300/sap/opu/odata/sap/Z_PRESENCE_SRV/GetReasonsSet('00102236')",
          "type" : "Z_PRESENCE_SRV.GetReasons"
        },
        "ReportHours" : false,
        "IvCaller" : "",
        "ReportFullDays" : true,
        "IvUserName" : "",
        "CompleteDay" : true,
        "IvPersonnelNumber" : "00000000",
        "IvDate" : null,
        "IvPossiblePeriodReport" : "",
        "Pernr" : "00102236",
        "Date" : "\/Date(1779148800000)\/",
        "Code" : "0200",
        "TextCode" : "מחלה",
        "TimeInfty" : "2001",
        "PeriodReport" : true,
        "ManagerApprove" : true,
        "AdministratorApprove" : false,
        "AddFile" : true,
        "ReportComment" : false,
        "AdditionalAbsenceData" : false
      },
      {
        "__metadata" : {
          "id" : "https://DEVSAPHRAPP01.ips.gov.il:4300/sap/opu/odata/sap/Z_PRESENCE_SRV/GetReasonsSet('00102236')",
          "uri" : "https://DEVSAPHRAPP01.ips.gov.il:4300/sap/opu/odata/sap/Z_PRESENCE_SRV/GetReasonsSet('00102236')",
          "type" : "Z_PRESENCE_SRV.GetReasons"
        },
        "ReportHours" : false,
        "IvCaller" : "",
        "ReportFullDays" : true,
        "IvUserName" : "",
        "CompleteDay" : true,
        "IvPersonnelNumber" : "00000000",
        "IvDate" : null,
        "IvPossiblePeriodReport" : "",
        "Pernr" : "00102236",
        "Date" : "\/Date(1779148800000)\/",
        "Code" : "0202",
        "TextCode" : "מחלה כרונית",
        "TimeInfty" : "2001",
        "PeriodReport" : true,
        "ManagerApprove" : true,
        "AdministratorApprove" : false,
        "AddFile" : true,
        "ReportComment" : false,
        "AdditionalAbsenceData" : false
      },
      {
        "__metadata" : {
          "id" : "https://DEVSAPHRAPP01.ips.gov.il:4300/sap/opu/odata/sap/Z_PRESENCE_SRV/GetReasonsSet('00102236')",
          "uri" : "https://DEVSAPHRAPP01.ips.gov.il:4300/sap/opu/odata/sap/Z_PRESENCE_SRV/GetReasonsSet('00102236')",
          "type" : "Z_PRESENCE_SRV.GetReasons"
        },
        "ReportHours" : false,
        "IvCaller" : "",
        "ReportFullDays" : false,
        "IvUserName" : "",
        "CompleteDay" : false,
        "IvPersonnelNumber" : "00000000",
        "IvDate" : null,
        "IvPossiblePeriodReport" : "",
        "Pernr" : "00102236",
        "Date" : "\/Date(1779148800000)\/",
        "Code" : "0204",
        "TextCode" : "מחלה בגין הריון",
        "TimeInfty" : "2001",
        "PeriodReport" : true,
        "ManagerApprove" : true,
        "AdministratorApprove" : false,
        "AddFile" : true,
        "ReportComment" : false,
        "AdditionalAbsenceData" : false
      },
      {
        "__metadata" : {
          "id" : "https://DEVSAPHRAPP01.ips.gov.il:4300/sap/opu/odata/sap/Z_PRESENCE_SRV/GetReasonsSet('00102236')",
          "uri" : "https://DEVSAPHRAPP01.ips.gov.il:4300/sap/opu/odata/sap/Z_PRESENCE_SRV/GetReasonsSet('00102236')",
          "type" : "Z_PRESENCE_SRV.GetReasons"
        },
        "ReportHours" : true,
        "IvCaller" : "",
        "ReportFullDays" : false,
        "IvUserName" : "",
        "CompleteDay" : false,
        "IvPersonnelNumber" : "00000000",
        "IvDate" : null,
        "IvPossiblePeriodReport" : "",
        "Pernr" : "00102236",
        "Date" : "\/Date(1779148800000)\/",
        "Code" : "0206",
        "TextCode" : "ביקור במרפאה",
        "TimeInfty" : "2001",
        "PeriodReport" : false,
        "ManagerApprove" : true,
        "AdministratorApprove" : false,
        "AddFile" : true,
        "ReportComment" : false,
        "AdditionalAbsenceData" : false
      },
      {
        "__metadata" : {
          "id" : "https://DEVSAPHRAPP01.ips.gov.il:4300/sap/opu/odata/sap/Z_PRESENCE_SRV/GetReasonsSet('00102236')",
          "uri" : "https://DEVSAPHRAPP01.ips.gov.il:4300/sap/opu/odata/sap/Z_PRESENCE_SRV/GetReasonsSet('00102236')",
          "type" : "Z_PRESENCE_SRV.GetReasons"
        },
        "ReportHours" : false,
        "IvCaller" : "",
        "ReportFullDays" : false,
        "IvUserName" : "",
        "CompleteDay" : false,
        "IvPersonnelNumber" : "00000000",
        "IvDate" : null,
        "IvPossiblePeriodReport" : "",
        "Pernr" : "00102236",
        "Date" : "\/Date(1779148800000)\/",
        "Code" : "0207",
        "TextCode" : "ועדה רפואית",
        "TimeInfty" : "2001",
        "PeriodReport" : false,
        "ManagerApprove" : false,
        "AdministratorApprove" : false,
        "AddFile" : false,
        "ReportComment" : false,
        "AdditionalAbsenceData" : false
      },
      {
        "__metadata" : {
          "id" : "https://DEVSAPHRAPP01.ips.gov.il:4300/sap/opu/odata/sap/Z_PRESENCE_SRV/GetReasonsSet('00102236')",
          "uri" : "https://DEVSAPHRAPP01.ips.gov.il:4300/sap/opu/odata/sap/Z_PRESENCE_SRV/GetReasonsSet('00102236')",
          "type" : "Z_PRESENCE_SRV.GetReasons"
        },
        "ReportHours" : true,
        "IvCaller" : "",
        "ReportFullDays" : false,
        "IvUserName" : "",
        "CompleteDay" : false,
        "IvPersonnelNumber" : "00000000",
        "IvDate" : null,
        "IvPossiblePeriodReport" : "",
        "Pernr" : "00102236",
        "Date" : "\/Date(1779148800000)\/",
        "Code" : "0208",
        "TextCode" : "בדיקה רפואית מבחן מאמץ",
        "TimeInfty" : "2001",
        "PeriodReport" : false,
        "ManagerApprove" : false,
        "AdministratorApprove" : false,
        "AddFile" : false,
        "ReportComment" : false,
        "AdditionalAbsenceData" : false
      },
      {
        "__metadata" : {
          "id" : "https://DEVSAPHRAPP01.ips.gov.il:4300/sap/opu/odata/sap/Z_PRESENCE_SRV/GetReasonsSet('00102236')",
          "uri" : "https://DEVSAPHRAPP01.ips.gov.il:4300/sap/opu/odata/sap/Z_PRESENCE_SRV/GetReasonsSet('00102236')",
          "type" : "Z_PRESENCE_SRV.GetReasons"
        },
        "ReportHours" : false,
        "IvCaller" : "",
        "ReportFullDays" : true,
        "IvUserName" : "",
        "CompleteDay" : false,
        "IvPersonnelNumber" : "00000000",
        "IvDate" : null,
        "IvPossiblePeriodReport" : "",
        "Pernr" : "00102236",
        "Date" : "\/Date(1779148800000)\/",
        "Code" : "0210",
        "TextCode" : "הצהרה",
        "TimeInfty" : "2001",
        "PeriodReport" : true,
        "ManagerApprove" : false,
        "AdministratorApprove" : false,
        "AddFile" : false,
        "ReportComment" : false,
        "AdditionalAbsenceData" : false
      },
      {
        "__metadata" : {
          "id" : "https://DEVSAPHRAPP01.ips.gov.il:4300/sap/opu/odata/sap/Z_PRESENCE_SRV/GetReasonsSet('00102236')",
          "uri" : "https://DEVSAPHRAPP01.ips.gov.il:4300/sap/opu/odata/sap/Z_PRESENCE_SRV/GetReasonsSet('00102236')",
          "type" : "Z_PRESENCE_SRV.GetReasons"
        },
        "ReportHours" : false,
        "IvCaller" : "",
        "ReportFullDays" : false,
        "IvUserName" : "",
        "CompleteDay" : false,
        "IvPersonnelNumber" : "00000000",
        "IvDate" : null,
        "IvPossiblePeriodReport" : "",
        "Pernr" : "00102236",
        "Date" : "\/Date(1779148800000)\/",
        "Code" : "0220",
        "TextCode" : "מחלת ילד",
        "TimeInfty" : "2001",
        "PeriodReport" : true,
        "ManagerApprove" : true,
        "AdministratorApprove" : false,
        "AddFile" : true,
        "ReportComment" : false,
        "AdditionalAbsenceData" : false
      },
      {
        "__metadata" : {
          "id" : "https://DEVSAPHRAPP01.ips.gov.il:4300/sap/opu/odata/sap/Z_PRESENCE_SRV/GetReasonsSet('00102236')",
          "uri" : "https://DEVSAPHRAPP01.ips.gov.il:4300/sap/opu/odata/sap/Z_PRESENCE_SRV/GetReasonsSet('00102236')",
          "type" : "Z_PRESENCE_SRV.GetReasons"
        },
        "ReportHours" : false,
        "IvCaller" : "",
        "ReportFullDays" : false,
        "IvUserName" : "",
        "CompleteDay" : false,
        "IvPersonnelNumber" : "00000000",
        "IvDate" : null,
        "IvPossiblePeriodReport" : "",
        "Pernr" : "00102236",
        "Date" : "\/Date(1779148800000)\/",
        "Code" : "0230",
        "TextCode" : "מחלת הורה",
        "TimeInfty" : "2001",
        "PeriodReport" : true,
        "ManagerApprove" : true,
        "AdministratorApprove" : false,
        "AddFile" : true,
        "ReportComment" : false,
        "AdditionalAbsenceData" : false
      },
      {
        "__metadata" : {
          "id" : "https://DEVSAPHRAPP01.ips.gov.il:4300/sap/opu/odata/sap/Z_PRESENCE_SRV/GetReasonsSet('00102236')",
          "uri" : "https://DEVSAPHRAPP01.ips.gov.il:4300/sap/opu/odata/sap/Z_PRESENCE_SRV/GetReasonsSet('00102236')",
          "type" : "Z_PRESENCE_SRV.GetReasons"
        },
        "ReportHours" : false,
        "IvCaller" : "",
        "ReportFullDays" : false,
        "IvUserName" : "",
        "CompleteDay" : false,
        "IvPersonnelNumber" : "00000000",
        "IvDate" : null,
        "IvPossiblePeriodReport" : "",
        "Pernr" : "00102236",
        "Date" : "\/Date(1779148800000)\/",
        "Code" : "0240",
        "TextCode" : "מחלה בן/בת זוג",
        "TimeInfty" : "2001",
        "PeriodReport" : true,
        "ManagerApprove" : true,
        "AdministratorApprove" : false,
        "AddFile" : true,
        "ReportComment" : false,
        "AdditionalAbsenceData" : false
      },
      {
        "__metadata" : {
          "id" : "https://DEVSAPHRAPP01.ips.gov.il:4300/sap/opu/odata/sap/Z_PRESENCE_SRV/GetReasonsSet('00102236')",
          "uri" : "https://DEVSAPHRAPP01.ips.gov.il:4300/sap/opu/odata/sap/Z_PRESENCE_SRV/GetReasonsSet('00102236')",
          "type" : "Z_PRESENCE_SRV.GetReasons"
        },
        "ReportHours" : false,
        "IvCaller" : "",
        "ReportFullDays" : false,
        "IvUserName" : "",
        "CompleteDay" : false,
        "IvPersonnelNumber" : "00000000",
        "IvDate" : null,
        "IvPossiblePeriodReport" : "",
        "Pernr" : "00102236",
        "Date" : "\/Date(1779148800000)\/",
        "Code" : "0250",
        "TextCode" : "הריון/לידה בת זוג",
        "TimeInfty" : "2001",
        "PeriodReport" : true,
        "ManagerApprove" : true,
        "AdministratorApprove" : false,
        "AddFile" : true,
        "ReportComment" : false,
        "AdditionalAbsenceData" : false
      },
      {
        "__metadata" : {
          "id" : "https://DEVSAPHRAPP01.ips.gov.il:4300/sap/opu/odata/sap/Z_PRESENCE_SRV/GetReasonsSet('00102236')",
          "uri" : "https://DEVSAPHRAPP01.ips.gov.il:4300/sap/opu/odata/sap/Z_PRESENCE_SRV/GetReasonsSet('00102236')",
          "type" : "Z_PRESENCE_SRV.GetReasons"
        },
        "ReportHours" : false,
        "IvCaller" : "",
        "ReportFullDays" : false,
        "IvUserName" : "",
        "CompleteDay" : false,
        "IvPersonnelNumber" : "00000000",
        "IvDate" : null,
        "IvPossiblePeriodReport" : "",
        "Pernr" : "00102236",
        "Date" : "\/Date(1779148800000)\/",
        "Code" : "0260",
        "TextCode" : "מחלה ממארת של ילד",
        "TimeInfty" : "2001",
        "PeriodReport" : true,
        "ManagerApprove" : true,
        "AdministratorApprove" : false,
        "AddFile" : true,
        "ReportComment" : false,
        "AdditionalAbsenceData" : false
      },
      {
        "__metadata" : {
          "id" : "https://DEVSAPHRAPP01.ips.gov.il:4300/sap/opu/odata/sap/Z_PRESENCE_SRV/GetReasonsSet('00102236')",
          "uri" : "https://DEVSAPHRAPP01.ips.gov.il:4300/sap/opu/odata/sap/Z_PRESENCE_SRV/GetReasonsSet('00102236')",
          "type" : "Z_PRESENCE_SRV.GetReasons"
        },
        "ReportHours" : false,
        "IvCaller" : "",
        "ReportFullDays" : false,
        "IvUserName" : "",
        "CompleteDay" : false,
        "IvPersonnelNumber" : "00000000",
        "IvDate" : null,
        "IvPossiblePeriodReport" : "",
        "Pernr" : "00102236",
        "Date" : "\/Date(1779148800000)\/",
        "Code" : "0265",
        "TextCode" : "מחלה קשה של ילד",
        "TimeInfty" : "2001",
        "PeriodReport" : true,
        "ManagerApprove" : true,
        "AdministratorApprove" : false,
        "AddFile" : true,
        "ReportComment" : false,
        "AdditionalAbsenceData" : false
      },
      {
        "__metadata" : {
          "id" : "https://DEVSAPHRAPP01.ips.gov.il:4300/sap/opu/odata/sap/Z_PRESENCE_SRV/GetReasonsSet('00102236')",
          "uri" : "https://DEVSAPHRAPP01.ips.gov.il:4300/sap/opu/odata/sap/Z_PRESENCE_SRV/GetReasonsSet('00102236')",
          "type" : "Z_PRESENCE_SRV.GetReasons"
        },
        "ReportHours" : false,
        "IvCaller" : "",
        "ReportFullDays" : false,
        "IvUserName" : "",
        "CompleteDay" : false,
        "IvPersonnelNumber" : "00000000",
        "IvDate" : null,
        "IvPossiblePeriodReport" : "",
        "Pernr" : "00102236",
        "Date" : "\/Date(1779148800000)\/",
        "Code" : "0270",
        "TextCode" : "מחלה ממארת של בן זוג",
        "TimeInfty" : "2001",
        "PeriodReport" : true,
        "ManagerApprove" : true,
        "AdministratorApprove" : false,
        "AddFile" : true,
        "ReportComment" : false,
        "AdditionalAbsenceData" : false
      },
      {
        "__metadata" : {
          "id" : "https://DEVSAPHRAPP01.ips.gov.il:4300/sap/opu/odata/sap/Z_PRESENCE_SRV/GetReasonsSet('00102236')",
          "uri" : "https://DEVSAPHRAPP01.ips.gov.il:4300/sap/opu/odata/sap/Z_PRESENCE_SRV/GetReasonsSet('00102236')",
          "type" : "Z_PRESENCE_SRV.GetReasons"
        },
        "ReportHours" : false,
        "IvCaller" : "",
        "ReportFullDays" : false,
        "IvUserName" : "",
        "CompleteDay" : false,
        "IvPersonnelNumber" : "00000000",
        "IvDate" : null,
        "IvPossiblePeriodReport" : "",
        "Pernr" : "00102236",
        "Date" : "\/Date(1779148800000)\/",
        "Code" : "0275",
        "TextCode" : "מחלה קשה של בן משפחה",
        "TimeInfty" : "2001",
        "PeriodReport" : true,
        "ManagerApprove" : true,
        "AdministratorApprove" : false,
        "AddFile" : true,
        "ReportComment" : false,
        "AdditionalAbsenceData" : false
      },
      {
        "__metadata" : {
          "id" : "https://DEVSAPHRAPP01.ips.gov.il:4300/sap/opu/odata/sap/Z_PRESENCE_SRV/GetReasonsSet('00102236')",
          "uri" : "https://DEVSAPHRAPP01.ips.gov.il:4300/sap/opu/odata/sap/Z_PRESENCE_SRV/GetReasonsSet('00102236')",
          "type" : "Z_PRESENCE_SRV.GetReasons"
        },
        "ReportHours" : false,
        "IvCaller" : "",
        "ReportFullDays" : false,
        "IvUserName" : "",
        "CompleteDay" : false,
        "IvPersonnelNumber" : "00000000",
        "IvDate" : null,
        "IvPossiblePeriodReport" : "",
        "Pernr" : "00102236",
        "Date" : "\/Date(1779148800000)\/",
        "Code" : "0280",
        "TextCode" : "טיפולי פוריות",
        "TimeInfty" : "2001",
        "PeriodReport" : true,
        "ManagerApprove" : true,
        "AdministratorApprove" : false,
        "AddFile" : true,
        "ReportComment" : false,
        "AdditionalAbsenceData" : false
      },
      {
        "__metadata" : {
          "id" : "https://DEVSAPHRAPP01.ips.gov.il:4300/sap/opu/odata/sap/Z_PRESENCE_SRV/GetReasonsSet('00102236')",
          "uri" : "https://DEVSAPHRAPP01.ips.gov.il:4300/sap/opu/odata/sap/Z_PRESENCE_SRV/GetReasonsSet('00102236')",
          "type" : "Z_PRESENCE_SRV.GetReasons"
        },
        "ReportHours" : true,
        "IvCaller" : "",
        "ReportFullDays" : false,
        "IvUserName" : "",
        "CompleteDay" : false,
        "IvPersonnelNumber" : "00000000",
        "IvDate" : null,
        "IvPossiblePeriodReport" : "",
        "Pernr" : "00102236",
        "Date" : "\/Date(1779148800000)\/",
        "Code" : "0300",
        "TextCode" : "שעות הריון",
        "TimeInfty" : "2001",
        "PeriodReport" : false,
        "ManagerApprove" : true,
        "AdministratorApprove" : false,
        "AddFile" : true,
        "ReportComment" : false,
        "AdditionalAbsenceData" : false
      },
      {
        "__metadata" : {
          "id" : "https://DEVSAPHRAPP01.ips.gov.il:4300/sap/opu/odata/sap/Z_PRESENCE_SRV/GetReasonsSet('00102236')",
          "uri" : "https://DEVSAPHRAPP01.ips.gov.il:4300/sap/opu/odata/sap/Z_PRESENCE_SRV/GetReasonsSet('00102236')",
          "type" : "Z_PRESENCE_SRV.GetReasons"
        },
        "ReportHours" : false,
        "IvCaller" : "",
        "ReportFullDays" : false,
        "IvUserName" : "",
        "CompleteDay" : false,
        "IvPersonnelNumber" : "00000000",
        "IvDate" : null,
        "IvPossiblePeriodReport" : "",
        "Pernr" : "00102236",
        "Date" : "\/Date(1779148800000)\/",
        "Code" : "0305",
        "TextCode" : "סיוע לילד עם מוגבלות",
        "TimeInfty" : "2001",
        "PeriodReport" : true,
        "ManagerApprove" : false,
        "AdministratorApprove" : false,
        "AddFile" : false,
        "ReportComment" : false,
        "AdditionalAbsenceData" : false
      },
      {
        "__metadata" : {
          "id" : "https://DEVSAPHRAPP01.ips.gov.il:4300/sap/opu/odata/sap/Z_PRESENCE_SRV/GetReasonsSet('00102236')",
          "uri" : "https://DEVSAPHRAPP01.ips.gov.il:4300/sap/opu/odata/sap/Z_PRESENCE_SRV/GetReasonsSet('00102236')",
          "type" : "Z_PRESENCE_SRV.GetReasons"
        },
        "ReportHours" : true,
        "IvCaller" : "",
        "ReportFullDays" : false,
        "IvUserName" : "",
        "CompleteDay" : false,
        "IvPersonnelNumber" : "00000000",
        "IvDate" : null,
        "IvPossiblePeriodReport" : "",
        "Pernr" : "00102236",
        "Date" : "\/Date(1779148800000)\/",
        "Code" : "0310",
        "TextCode" : "שעות סיוע ילד מוגבלות",
        "TimeInfty" : "2001",
        "PeriodReport" : false,
        "ManagerApprove" : false,
        "AdministratorApprove" : false,
        "AddFile" : false,
        "ReportComment" : false,
        "AdditionalAbsenceData" : false
      },
      {
        "__metadata" : {
          "id" : "https://DEVSAPHRAPP01.ips.gov.il:4300/sap/opu/odata/sap/Z_PRESENCE_SRV/GetReasonsSet('00102236')",
          "uri" : "https://DEVSAPHRAPP01.ips.gov.il:4300/sap/opu/odata/sap/Z_PRESENCE_SRV/GetReasonsSet('00102236')",
          "type" : "Z_PRESENCE_SRV.GetReasons"
        },
        "ReportHours" : false,
        "IvCaller" : "",
        "ReportFullDays" : true,
        "IvUserName" : "",
        "CompleteDay" : true,
        "IvPersonnelNumber" : "00000000",
        "IvDate" : null,
        "IvPossiblePeriodReport" : "",
        "Pernr" : "00102236",
        "Date" : "\/Date(1779148800000)\/",
        "Code" : "0400",
        "TextCode" : "תאונת דרכים בתפקיד",
        "TimeInfty" : "2001",
        "PeriodReport" : true,
        "ManagerApprove" : true,
        "AdministratorApprove" : false,
        "AddFile" : true,
        "ReportComment" : false,
        "AdditionalAbsenceData" : false
      },
      {
        "__metadata" : {
          "id" : "https://DEVSAPHRAPP01.ips.gov.il:4300/sap/opu/odata/sap/Z_PRESENCE_SRV/GetReasonsSet('00102236')",
          "uri" : "https://DEVSAPHRAPP01.ips.gov.il:4300/sap/opu/odata/sap/Z_PRESENCE_SRV/GetReasonsSet('00102236')",
          "type" : "Z_PRESENCE_SRV.GetReasons"
        },
        "ReportHours" : false,
        "IvCaller" : "",
        "ReportFullDays" : true,
        "IvUserName" : "",
        "CompleteDay" : true,
        "IvPersonnelNumber" : "00000000",
        "IvDate" : null,
        "IvPossiblePeriodReport" : "",
        "Pernr" : "00102236",
        "Date" : "\/Date(1779148800000)\/",
        "Code" : "0410",
        "TextCode" : "תאונת עבודה בתפקיד",
        "TimeInfty" : "2001",
        "PeriodReport" : true,
        "ManagerApprove" : true,
        "AdministratorApprove" : false,
        "AddFile" : true,
        "ReportComment" : false,
        "AdditionalAbsenceData" : false
      },
      {
        "__metadata" : {
          "id" : "https://DEVSAPHRAPP01.ips.gov.il:4300/sap/opu/odata/sap/Z_PRESENCE_SRV/GetReasonsSet('00102236')",
          "uri" : "https://DEVSAPHRAPP01.ips.gov.il:4300/sap/opu/odata/sap/Z_PRESENCE_SRV/GetReasonsSet('00102236')",
          "type" : "Z_PRESENCE_SRV.GetReasons"
        },
        "ReportHours" : false,
        "IvCaller" : "",
        "ReportFullDays" : true,
        "IvUserName" : "",
        "CompleteDay" : true,
        "IvPersonnelNumber" : "00000000",
        "IvDate" : null,
        "IvPossiblePeriodReport" : "",
        "Pernr" : "00102236",
        "Date" : "\/Date(1779148800000)\/",
        "Code" : "0420",
        "TextCode" : "מחלה משהב\"ט",
        "TimeInfty" : "2001",
        "PeriodReport" : true,
        "ManagerApprove" : true,
        "AdministratorApprove" : false,
        "AddFile" : true,
        "ReportComment" : false,
        "AdditionalAbsenceData" : false
      },
      {
        "__metadata" : {
          "id" : "https://DEVSAPHRAPP01.ips.gov.il:4300/sap/opu/odata/sap/Z_PRESENCE_SRV/GetReasonsSet('00102236')",
          "uri" : "https://DEVSAPHRAPP01.ips.gov.il:4300/sap/opu/odata/sap/Z_PRESENCE_SRV/GetReasonsSet('00102236')",
          "type" : "Z_PRESENCE_SRV.GetReasons"
        },
        "ReportHours" : false,
        "IvCaller" : "",
        "ReportFullDays" : true,
        "IvUserName" : "",
        "CompleteDay" : true,
        "IvPersonnelNumber" : "00000000",
        "IvDate" : null,
        "IvPossiblePeriodReport" : "",
        "Pernr" : "00102236",
        "Date" : "\/Date(1779148800000)\/",
        "Code" : "0500",
        "TextCode" : "אבל",
        "TimeInfty" : "2001",
        "PeriodReport" : true,
        "ManagerApprove" : true,
        "AdministratorApprove" : false,
        "AddFile" : true,
        "ReportComment" : false,
        "AdditionalAbsenceData" : false
      },
      {
        "__metadata" : {
          "id" : "https://DEVSAPHRAPP01.ips.gov.il:4300/sap/opu/odata/sap/Z_PRESENCE_SRV/GetReasonsSet('00102236')",
          "uri" : "https://DEVSAPHRAPP01.ips.gov.il:4300/sap/opu/odata/sap/Z_PRESENCE_SRV/GetReasonsSet('00102236')",
          "type" : "Z_PRESENCE_SRV.GetReasons"
        },
        "ReportHours" : false,
        "IvCaller" : "",
        "ReportFullDays" : true,
        "IvUserName" : "",
        "CompleteDay" : true,
        "IvPersonnelNumber" : "00000000",
        "IvDate" : null,
        "IvPossiblePeriodReport" : "",
        "Pernr" : "00102236",
        "Date" : "\/Date(1779148800000)\/",
        "Code" : "0505",
        "TextCode" : "קיצור צום",
        "TimeInfty" : "2001",
        "PeriodReport" : false,
        "ManagerApprove" : false,
        "AdministratorApprove" : false,
        "AddFile" : false,
        "ReportComment" : false,
        "AdditionalAbsenceData" : false
      },
      {
        "__metadata" : {
          "id" : "https://DEVSAPHRAPP01.ips.gov.il:4300/sap/opu/odata/sap/Z_PRESENCE_SRV/GetReasonsSet('00102236')",
          "uri" : "https://DEVSAPHRAPP01.ips.gov.il:4300/sap/opu/odata/sap/Z_PRESENCE_SRV/GetReasonsSet('00102236')",
          "type" : "Z_PRESENCE_SRV.GetReasons"
        },
        "ReportHours" : false,
        "IvCaller" : "",
        "ReportFullDays" : true,
        "IvUserName" : "",
        "CompleteDay" : false,
        "IvPersonnelNumber" : "00000000",
        "IvDate" : null,
        "IvPossiblePeriodReport" : "",
        "Pernr" : "00102236",
        "Date" : "\/Date(1779148800000)\/",
        "Code" : "0510",
        "TextCode" : "יום אזכרה שנתי",
        "TimeInfty" : "2001",
        "PeriodReport" : false,
        "ManagerApprove" : false,
        "AdministratorApprove" : false,
        "AddFile" : false,
        "ReportComment" : false,
        "AdditionalAbsenceData" : false
      },
      {
        "__metadata" : {
          "id" : "https://DEVSAPHRAPP01.ips.gov.il:4300/sap/opu/odata/sap/Z_PRESENCE_SRV/GetReasonsSet('00102236')",
          "uri" : "https://DEVSAPHRAPP01.ips.gov.il:4300/sap/opu/odata/sap/Z_PRESENCE_SRV/GetReasonsSet('00102236')",
          "type" : "Z_PRESENCE_SRV.GetReasons"
        },
        "ReportHours" : false,
        "IvCaller" : "",
        "ReportFullDays" : false,
        "IvUserName" : "",
        "CompleteDay" : true,
        "IvPersonnelNumber" : "00000000",
        "IvDate" : null,
        "IvPossiblePeriodReport" : "",
        "Pernr" : "00102236",
        "Date" : "\/Date(1779148800000)\/",
        "Code" : "0515",
        "TextCode" : "היעדרות בתפקיד",
        "TimeInfty" : "2001",
        "PeriodReport" : true,
        "ManagerApprove" : false,
        "AdministratorApprove" : false,
        "AddFile" : false,
        "ReportComment" : false,
        "AdditionalAbsenceData" : false
      },
      {
        "__metadata" : {
          "id" : "https://DEVSAPHRAPP01.ips.gov.il:4300/sap/opu/odata/sap/Z_PRESENCE_SRV/GetReasonsSet('00102236')",
          "uri" : "https://DEVSAPHRAPP01.ips.gov.il:4300/sap/opu/odata/sap/Z_PRESENCE_SRV/GetReasonsSet('00102236')",
          "type" : "Z_PRESENCE_SRV.GetReasons"
        },
        "ReportHours" : true,
        "IvCaller" : "",
        "ReportFullDays" : false,
        "IvUserName" : "",
        "CompleteDay" : false,
        "IvPersonnelNumber" : "00000000",
        "IvDate" : null,
        "IvPossiblePeriodReport" : "",
        "Pernr" : "00102236",
        "Date" : "\/Date(1779148800000)\/",
        "Code" : "0525",
        "TextCode" : "ניחום אבלים/הלוויה",
        "TimeInfty" : "2001",
        "PeriodReport" : false,
        "ManagerApprove" : false,
        "AdministratorApprove" : false,
        "AddFile" : false,
        "ReportComment" : false,
        "AdditionalAbsenceData" : false
      },
      {
        "__metadata" : {
          "id" : "https://DEVSAPHRAPP01.ips.gov.il:4300/sap/opu/odata/sap/Z_PRESENCE_SRV/GetReasonsSet('00102236')",
          "uri" : "https://DEVSAPHRAPP01.ips.gov.il:4300/sap/opu/odata/sap/Z_PRESENCE_SRV/GetReasonsSet('00102236')",
          "type" : "Z_PRESENCE_SRV.GetReasons"
        },
        "ReportHours" : false,
        "IvCaller" : "",
        "ReportFullDays" : true,
        "IvUserName" : "",
        "CompleteDay" : true,
        "IvPersonnelNumber" : "00000000",
        "IvDate" : null,
        "IvPossiblePeriodReport" : "",
        "Pernr" : "00102236",
        "Date" : "\/Date(1779148800000)\/",
        "Code" : "0530",
        "TextCode" : "שבסטיבל",
        "TimeInfty" : "2001",
        "PeriodReport" : false,
        "ManagerApprove" : true,
        "AdministratorApprove" : false,
        "AddFile" : false,
        "ReportComment" : false,
        "AdditionalAbsenceData" : false
      },
      {
        "__metadata" : {
          "id" : "https://DEVSAPHRAPP01.ips.gov.il:4300/sap/opu/odata/sap/Z_PRESENCE_SRV/GetReasonsSet('00102236')",
          "uri" : "https://DEVSAPHRAPP01.ips.gov.il:4300/sap/opu/odata/sap/Z_PRESENCE_SRV/GetReasonsSet('00102236')",
          "type" : "Z_PRESENCE_SRV.GetReasons"
        },
        "ReportHours" : false,
        "IvCaller" : "",
        "ReportFullDays" : true,
        "IvUserName" : "",
        "CompleteDay" : true,
        "IvPersonnelNumber" : "00000000",
        "IvDate" : null,
        "IvPossiblePeriodReport" : "",
        "Pernr" : "00102236",
        "Date" : "\/Date(1779148800000)\/",
        "Code" : "0535",
        "TextCode" : "שלישי משפחתי",
        "TimeInfty" : "2001",
        "PeriodReport" : false,
        "ManagerApprove" : false,
        "AdministratorApprove" : false,
        "AddFile" : false,
        "ReportComment" : false,
        "AdditionalAbsenceData" : false
      },
      {
        "__metadata" : {
          "id" : "https://DEVSAPHRAPP01.ips.gov.il:4300/sap/opu/odata/sap/Z_PRESENCE_SRV/GetReasonsSet('00102236')",
          "uri" : "https://DEVSAPHRAPP01.ips.gov.il:4300/sap/opu/odata/sap/Z_PRESENCE_SRV/GetReasonsSet('00102236')",
          "type" : "Z_PRESENCE_SRV.GetReasons"
        },
        "ReportHours" : false,
        "IvCaller" : "",
        "ReportFullDays" : true,
        "IvUserName" : "",
        "CompleteDay" : false,
        "IvPersonnelNumber" : "00000000",
        "IvDate" : null,
        "IvPossiblePeriodReport" : "",
        "Pernr" : "00102236",
        "Date" : "\/Date(1779148800000)\/",
        "Code" : "0540",
        "TextCode" : "נישואין",
        "TimeInfty" : "2001",
        "PeriodReport" : false,
        "ManagerApprove" : false,
        "AdministratorApprove" : false,
        "AddFile" : false,
        "ReportComment" : false,
        "AdditionalAbsenceData" : false
      },
      {
        "__metadata" : {
          "id" : "https://DEVSAPHRAPP01.ips.gov.il:4300/sap/opu/odata/sap/Z_PRESENCE_SRV/GetReasonsSet('00102236')",
          "uri" : "https://DEVSAPHRAPP01.ips.gov.il:4300/sap/opu/odata/sap/Z_PRESENCE_SRV/GetReasonsSet('00102236')",
          "type" : "Z_PRESENCE_SRV.GetReasons"
        },
        "ReportHours" : false,
        "IvCaller" : "",
        "ReportFullDays" : true,
        "IvUserName" : "",
        "CompleteDay" : true,
        "IvPersonnelNumber" : "00000000",
        "IvDate" : null,
        "IvPossiblePeriodReport" : "",
        "Pernr" : "00102236",
        "Date" : "\/Date(1779148800000)\/",
        "Code" : "0545",
        "TextCode" : "יום חופשי - לוחם מצדה",
        "TimeInfty" : "2001",
        "PeriodReport" : false,
        "ManagerApprove" : false,
        "AdministratorApprove" : false,
        "AddFile" : false,
        "ReportComment" : false,
        "AdditionalAbsenceData" : false
      },
      {
        "__metadata" : {
          "id" : "https://DEVSAPHRAPP01.ips.gov.il:4300/sap/opu/odata/sap/Z_PRESENCE_SRV/GetReasonsSet('00102236')",
          "uri" : "https://DEVSAPHRAPP01.ips.gov.il:4300/sap/opu/odata/sap/Z_PRESENCE_SRV/GetReasonsSet('00102236')",
          "type" : "Z_PRESENCE_SRV.GetReasons"
        },
        "ReportHours" : false,
        "IvCaller" : "",
        "ReportFullDays" : true,
        "IvUserName" : "",
        "CompleteDay" : true,
        "IvPersonnelNumber" : "00000000",
        "IvDate" : null,
        "IvPossiblePeriodReport" : "",
        "Pernr" : "00102236",
        "Date" : "\/Date(1779148800000)\/",
        "Code" : "0600",
        "TextCode" : "מילואים",
        "TimeInfty" : "2001",
        "PeriodReport" : true,
        "ManagerApprove" : true,
        "AdministratorApprove" : false,
        "AddFile" : true,
        "ReportComment" : false,
        "AdditionalAbsenceData" : false
      },
      {
        "__metadata" : {
          "id" : "https://DEVSAPHRAPP01.ips.gov.il:4300/sap/opu/odata/sap/Z_PRESENCE_SRV/GetReasonsSet('00102236')",
          "uri" : "https://DEVSAPHRAPP01.ips.gov.il:4300/sap/opu/odata/sap/Z_PRESENCE_SRV/GetReasonsSet('00102236')",
          "type" : "Z_PRESENCE_SRV.GetReasons"
        },
        "ReportHours" : false,
        "IvCaller" : "",
        "ReportFullDays" : false,
        "IvUserName" : "",
        "CompleteDay" : false,
        "IvPersonnelNumber" : "00000000",
        "IvDate" : null,
        "IvPossiblePeriodReport" : "",
        "Pernr" : "00102236",
        "Date" : "\/Date(1779148800000)\/",
        "Code" : "0700",
        "TextCode" : "פגרה",
        "TimeInfty" : "2001",
        "PeriodReport" : true,
        "ManagerApprove" : false,
        "AdministratorApprove" : false,
        "AddFile" : false,
        "ReportComment" : false,
        "AdditionalAbsenceData" : false
      },
      {
        "__metadata" : {
          "id" : "https://DEVSAPHRAPP01.ips.gov.il:4300/sap/opu/odata/sap/Z_PRESENCE_SRV/GetReasonsSet('00102236')",
          "uri" : "https://DEVSAPHRAPP01.ips.gov.il:4300/sap/opu/odata/sap/Z_PRESENCE_SRV/GetReasonsSet('00102236')",
          "type" : "Z_PRESENCE_SRV.GetReasons"
        },
        "ReportHours" : false,
        "IvCaller" : "",
        "ReportFullDays" : false,
        "IvUserName" : "",
        "CompleteDay" : false,
        "IvPersonnelNumber" : "00000000",
        "IvDate" : null,
        "IvPossiblePeriodReport" : "",
        "Pernr" : "00102236",
        "Date" : "\/Date(1779148800000)\/",
        "Code" : "0705",
        "TextCode" : "פגרת יום הולדת",
        "TimeInfty" : "2001",
        "PeriodReport" : false,
        "ManagerApprove" : false,
        "AdministratorApprove" : false,
        "AddFile" : false,
        "ReportComment" : false,
        "AdditionalAbsenceData" : false
      },
      {
        "__metadata" : {
          "id" : "https://DEVSAPHRAPP01.ips.gov.il:4300/sap/opu/odata/sap/Z_PRESENCE_SRV/GetReasonsSet('00102236')",
          "uri" : "https://DEVSAPHRAPP01.ips.gov.il:4300/sap/opu/odata/sap/Z_PRESENCE_SRV/GetReasonsSet('00102236')",
          "type" : "Z_PRESENCE_SRV.GetReasons"
        },
        "ReportHours" : false,
        "IvCaller" : "",
        "ReportFullDays" : true,
        "IvUserName" : "",
        "CompleteDay" : true,
        "IvPersonnelNumber" : "00000000",
        "IvDate" : null,
        "IvPossiblePeriodReport" : "",
        "Pernr" : "00102236",
        "Date" : "\/Date(1779148800000)\/",
        "Code" : "0710",
        "TextCode" : "פגרת מפקד",
        "TimeInfty" : "2001",
        "PeriodReport" : false,
        "ManagerApprove" : true,
        "AdministratorApprove" : false,
        "AddFile" : false,
        "ReportComment" : false,
        "AdditionalAbsenceData" : false
      },
      {
        "__metadata" : {
          "id" : "https://DEVSAPHRAPP01.ips.gov.il:4300/sap/opu/odata/sap/Z_PRESENCE_SRV/GetReasonsSet('00102236')",
          "uri" : "https://DEVSAPHRAPP01.ips.gov.il:4300/sap/opu/odata/sap/Z_PRESENCE_SRV/GetReasonsSet('00102236')",
          "type" : "Z_PRESENCE_SRV.GetReasons"
        },
        "ReportHours" : false,
        "IvCaller" : "",
        "ReportFullDays" : true,
        "IvUserName" : "",
        "CompleteDay" : true,
        "IvPersonnelNumber" : "00000000",
        "IvDate" : null,
        "IvPossiblePeriodReport" : "",
        "Pernr" : "00102236",
        "Date" : "\/Date(1779148800000)\/",
        "Code" : "0712",
        "TextCode" : "פגרת נציב",
        "TimeInfty" : "2001",
        "PeriodReport" : false,
        "ManagerApprove" : true,
        "AdministratorApprove" : false,
        "AddFile" : false,
        "ReportComment" : false,
        "AdditionalAbsenceData" : false
      },
      {
        "__metadata" : {
          "id" : "https://DEVSAPHRAPP01.ips.gov.il:4300/sap/opu/odata/sap/Z_PRESENCE_SRV/GetReasonsSet('00102236')",
          "uri" : "https://DEVSAPHRAPP01.ips.gov.il:4300/sap/opu/odata/sap/Z_PRESENCE_SRV/GetReasonsSet('00102236')",
          "type" : "Z_PRESENCE_SRV.GetReasons"
        },
        "ReportHours" : true,
        "IvCaller" : "",
        "ReportFullDays" : false,
        "IvUserName" : "",
        "CompleteDay" : false,
        "IvPersonnelNumber" : "00000000",
        "IvDate" : null,
        "IvPossiblePeriodReport" : "",
        "Pernr" : "00102236",
        "Date" : "\/Date(1779148800000)\/",
        "Code" : "0714",
        "TextCode" : "שעות ממונה",
        "TimeInfty" : "2001",
        "PeriodReport" : false,
        "ManagerApprove" : true,
        "AdministratorApprove" : false,
        "AddFile" : false,
        "ReportComment" : false,
        "AdditionalAbsenceData" : false
      },
      {
        "__metadata" : {
          "id" : "https://DEVSAPHRAPP01.ips.gov.il:4300/sap/opu/odata/sap/Z_PRESENCE_SRV/GetReasonsSet('00102236')",
          "uri" : "https://DEVSAPHRAPP01.ips.gov.il:4300/sap/opu/odata/sap/Z_PRESENCE_SRV/GetReasonsSet('00102236')",
          "type" : "Z_PRESENCE_SRV.GetReasons"
        },
        "ReportHours" : false,
        "IvCaller" : "",
        "ReportFullDays" : false,
        "IvUserName" : "",
        "CompleteDay" : false,
        "IvPersonnelNumber" : "00000000",
        "IvDate" : null,
        "IvPossiblePeriodReport" : "",
        "Pernr" : "00102236",
        "Date" : "\/Date(1779148800000)\/",
        "Code" : "0800",
        "TextCode" : "קורס",
        "TimeInfty" : "2001",
        "PeriodReport" : true,
        "ManagerApprove" : false,
        "AdministratorApprove" : false,
        "AddFile" : false,
        "ReportComment" : false,
        "AdditionalAbsenceData" : false
      },
      {
        "__metadata" : {
          "id" : "https://DEVSAPHRAPP01.ips.gov.il:4300/sap/opu/odata/sap/Z_PRESENCE_SRV/GetReasonsSet('00102236')",
          "uri" : "https://DEVSAPHRAPP01.ips.gov.il:4300/sap/opu/odata/sap/Z_PRESENCE_SRV/GetReasonsSet('00102236')",
          "type" : "Z_PRESENCE_SRV.GetReasons"
        },
        "ReportHours" : false,
        "IvCaller" : "",
        "ReportFullDays" : false,
        "IvUserName" : "",
        "CompleteDay" : false,
        "IvPersonnelNumber" : "00000000",
        "IvDate" : null,
        "IvPossiblePeriodReport" : "",
        "Pernr" : "00102236",
        "Date" : "\/Date(1779148800000)\/",
        "Code" : "0802",
        "TextCode" : "לימודים",
        "TimeInfty" : "2001",
        "PeriodReport" : false,
        "ManagerApprove" : false,
        "AdministratorApprove" : false,
        "AddFile" : false,
        "ReportComment" : false,
        "AdditionalAbsenceData" : false
      },
      {
        "__metadata" : {
          "id" : "https://DEVSAPHRAPP01.ips.gov.il:4300/sap/opu/odata/sap/Z_PRESENCE_SRV/GetReasonsSet('00102236')",
          "uri" : "https://DEVSAPHRAPP01.ips.gov.il:4300/sap/opu/odata/sap/Z_PRESENCE_SRV/GetReasonsSet('00102236')",
          "type" : "Z_PRESENCE_SRV.GetReasons"
        },
        "ReportHours" : false,
        "IvCaller" : "",
        "ReportFullDays" : false,
        "IvUserName" : "",
        "CompleteDay" : false,
        "IvPersonnelNumber" : "00000000",
        "IvDate" : null,
        "IvPossiblePeriodReport" : "",
        "Pernr" : "00102236",
        "Date" : "\/Date(1779148800000)\/",
        "Code" : "0805",
        "TextCode" : "יום עיון / השתלמות",
        "TimeInfty" : "2001",
        "PeriodReport" : true,
        "ManagerApprove" : false,
        "AdministratorApprove" : false,
        "AddFile" : false,
        "ReportComment" : false,
        "AdditionalAbsenceData" : false
      },
      {
        "__metadata" : {
          "id" : "https://DEVSAPHRAPP01.ips.gov.il:4300/sap/opu/odata/sap/Z_PRESENCE_SRV/GetReasonsSet('00102236')",
          "uri" : "https://DEVSAPHRAPP01.ips.gov.il:4300/sap/opu/odata/sap/Z_PRESENCE_SRV/GetReasonsSet('00102236')",
          "type" : "Z_PRESENCE_SRV.GetReasons"
        },
        "ReportHours" : false,
        "IvCaller" : "",
        "ReportFullDays" : false,
        "IvUserName" : "",
        "CompleteDay" : false,
        "IvPersonnelNumber" : "00000000",
        "IvDate" : null,
        "IvPossiblePeriodReport" : "",
        "Pernr" : "00102236",
        "Date" : "\/Date(1779148800000)\/",
        "Code" : "0810",
        "TextCode" : "יום יחידה",
        "TimeInfty" : "2001",
        "PeriodReport" : false,
        "ManagerApprove" : false,
        "AdministratorApprove" : false,
        "AddFile" : false,
        "ReportComment" : false,
        "AdditionalAbsenceData" : false
      },
      {
        "__metadata" : {
          "id" : "https://DEVSAPHRAPP01.ips.gov.il:4300/sap/opu/odata/sap/Z_PRESENCE_SRV/GetReasonsSet('00102236')",
          "uri" : "https://DEVSAPHRAPP01.ips.gov.il:4300/sap/opu/odata/sap/Z_PRESENCE_SRV/GetReasonsSet('00102236')",
          "type" : "Z_PRESENCE_SRV.GetReasons"
        },
        "ReportHours" : false,
        "IvCaller" : "",
        "ReportFullDays" : false,
        "IvUserName" : "",
        "CompleteDay" : false,
        "IvPersonnelNumber" : "00000000",
        "IvDate" : null,
        "IvPossiblePeriodReport" : "",
        "Pernr" : "00102236",
        "Date" : "\/Date(1779148800000)\/",
        "Code" : "0815",
        "TextCode" : "יום אוריינטציה",
        "TimeInfty" : "2001",
        "PeriodReport" : false,
        "ManagerApprove" : false,
        "AdministratorApprove" : false,
        "AddFile" : false,
        "ReportComment" : false,
        "AdditionalAbsenceData" : false
      },
      {
        "__metadata" : {
          "id" : "https://DEVSAPHRAPP01.ips.gov.il:4300/sap/opu/odata/sap/Z_PRESENCE_SRV/GetReasonsSet('00102236')",
          "uri" : "https://DEVSAPHRAPP01.ips.gov.il:4300/sap/opu/odata/sap/Z_PRESENCE_SRV/GetReasonsSet('00102236')",
          "type" : "Z_PRESENCE_SRV.GetReasons"
        },
        "ReportHours" : false,
        "IvCaller" : "",
        "ReportFullDays" : true,
        "IvUserName" : "",
        "CompleteDay" : true,
        "IvPersonnelNumber" : "00000000",
        "IvDate" : null,
        "IvPossiblePeriodReport" : "",
        "Pernr" : "00102236",
        "Date" : "\/Date(1779148800000)\/",
        "Code" : "0820",
        "TextCode" : "אימון חד יומי",
        "TimeInfty" : "2001",
        "PeriodReport" : false,
        "ManagerApprove" : true,
        "AdministratorApprove" : false,
        "AddFile" : false,
        "ReportComment" : false,
        "AdditionalAbsenceData" : false
      },
      {
        "__metadata" : {
          "id" : "https://DEVSAPHRAPP01.ips.gov.il:4300/sap/opu/odata/sap/Z_PRESENCE_SRV/GetReasonsSet('00102236')",
          "uri" : "https://DEVSAPHRAPP01.ips.gov.il:4300/sap/opu/odata/sap/Z_PRESENCE_SRV/GetReasonsSet('00102236')",
          "type" : "Z_PRESENCE_SRV.GetReasons"
        },
        "ReportHours" : false,
        "IvCaller" : "",
        "ReportFullDays" : true,
        "IvUserName" : "",
        "CompleteDay" : true,
        "IvPersonnelNumber" : "00000000",
        "IvDate" : null,
        "IvPossiblePeriodReport" : "",
        "Pernr" : "00102236",
        "Date" : "\/Date(1779148800000)\/",
        "Code" : "0822",
        "TextCode" : "יום מטווח",
        "TimeInfty" : "2001",
        "PeriodReport" : false,
        "ManagerApprove" : true,
        "AdministratorApprove" : false,
        "AddFile" : false,
        "ReportComment" : false,
        "AdditionalAbsenceData" : false
      },
      {
        "__metadata" : {
          "id" : "https://DEVSAPHRAPP01.ips.gov.il:4300/sap/opu/odata/sap/Z_PRESENCE_SRV/GetReasonsSet('00102236')",
          "uri" : "https://DEVSAPHRAPP01.ips.gov.il:4300/sap/opu/odata/sap/Z_PRESENCE_SRV/GetReasonsSet('00102236')",
          "type" : "Z_PRESENCE_SRV.GetReasons"
        },
        "ReportHours" : false,
        "IvCaller" : "",
        "ReportFullDays" : true,
        "IvUserName" : "",
        "CompleteDay" : true,
        "IvPersonnelNumber" : "00000000",
        "IvDate" : null,
        "IvPossiblePeriodReport" : "",
        "Pernr" : "00102236",
        "Date" : "\/Date(1779148800000)\/",
        "Code" : "0824",
        "TextCode" : "משימה ארגונית",
        "TimeInfty" : "2001",
        "PeriodReport" : false,
        "ManagerApprove" : true,
        "AdministratorApprove" : false,
        "AddFile" : false,
        "ReportComment" : false,
        "AdditionalAbsenceData" : false
      },
      {
        "__metadata" : {
          "id" : "https://DEVSAPHRAPP01.ips.gov.il:4300/sap/opu/odata/sap/Z_PRESENCE_SRV/GetReasonsSet('00102236')",
          "uri" : "https://DEVSAPHRAPP01.ips.gov.il:4300/sap/opu/odata/sap/Z_PRESENCE_SRV/GetReasonsSet('00102236')",
          "type" : "Z_PRESENCE_SRV.GetReasons"
        },
        "ReportHours" : true,
        "IvCaller" : "",
        "ReportFullDays" : false,
        "IvUserName" : "",
        "CompleteDay" : false,
        "IvPersonnelNumber" : "00000000",
        "IvDate" : null,
        "IvPossiblePeriodReport" : "",
        "Pernr" : "00102236",
        "Date" : "\/Date(1779148800000)\/",
        "Code" : "2100",
        "TextCode" : "פעילות גופנית",
        "TimeInfty" : "2002",
        "PeriodReport" : false,
        "ManagerApprove" : false,
        "AdministratorApprove" : false,
        "AddFile" : false,
        "ReportComment" : false,
        "AdditionalAbsenceData" : false
      },
      {
        "__metadata" : {
          "id" : "https://DEVSAPHRAPP01.ips.gov.il:4300/sap/opu/odata/sap/Z_PRESENCE_SRV/GetReasonsSet('00102236')",
          "uri" : "https://DEVSAPHRAPP01.ips.gov.il:4300/sap/opu/odata/sap/Z_PRESENCE_SRV/GetReasonsSet('00102236')",
          "type" : "Z_PRESENCE_SRV.GetReasons"
        },
        "ReportHours" : true,
        "IvCaller" : "",
        "ReportFullDays" : false,
        "IvUserName" : "",
        "CompleteDay" : false,
        "IvPersonnelNumber" : "00000000",
        "IvDate" : null,
        "IvPossiblePeriodReport" : "",
        "Pernr" : "00102236",
        "Date" : "\/Date(1779148800000)\/",
        "Code" : "2200",
        "TextCode" : "לימוד לגמול השתלמות",
        "TimeInfty" : "2002",
        "PeriodReport" : false,
        "ManagerApprove" : false,
        "AdministratorApprove" : false,
        "AddFile" : false,
        "ReportComment" : false,
        "AdditionalAbsenceData" : false
      },
      {
        "__metadata" : {
          "id" : "https://DEVSAPHRAPP01.ips.gov.il:4300/sap/opu/odata/sap/Z_PRESENCE_SRV/GetReasonsSet('00102236')",
          "uri" : "https://DEVSAPHRAPP01.ips.gov.il:4300/sap/opu/odata/sap/Z_PRESENCE_SRV/GetReasonsSet('00102236')",
          "type" : "Z_PRESENCE_SRV.GetReasons"
        },
        "ReportHours" : false,
        "IvCaller" : "",
        "ReportFullDays" : false,
        "IvUserName" : "",
        "CompleteDay" : false,
        "IvPersonnelNumber" : "00000000",
        "IvDate" : null,
        "IvPossiblePeriodReport" : "",
        "Pernr" : "00102236",
        "Date" : "\/Date(1779148800000)\/",
        "Code" : "2300",
        "TextCode" : "תחרות ריצה",
        "TimeInfty" : "2002",
        "PeriodReport" : false,
        "ManagerApprove" : true,
        "AdministratorApprove" : false,
        "AddFile" : false,
        "ReportComment" : false,
        "AdditionalAbsenceData" : false
      },
      {
        "__metadata" : {
          "id" : "https://DEVSAPHRAPP01.ips.gov.il:4300/sap/opu/odata/sap/Z_PRESENCE_SRV/GetReasonsSet('00102236')",
          "uri" : "https://DEVSAPHRAPP01.ips.gov.il:4300/sap/opu/odata/sap/Z_PRESENCE_SRV/GetReasonsSet('00102236')",
          "type" : "Z_PRESENCE_SRV.GetReasons"
        },
        "ReportHours" : false,
        "IvCaller" : "",
        "ReportFullDays" : false,
        "IvUserName" : "",
        "CompleteDay" : false,
        "IvPersonnelNumber" : "00000000",
        "IvDate" : null,
        "IvPossiblePeriodReport" : "",
        "Pernr" : "00102236",
        "Date" : "\/Date(1779148800000)\/",
        "Code" : "2310",
        "TextCode" : "תחרות ירי/ניווט/מרתון מלא",
        "TimeInfty" : "2002",
        "PeriodReport" : false,
        "ManagerApprove" : true,
        "AdministratorApprove" : false,
        "AddFile" : false,
        "ReportComment" : false,
        "AdditionalAbsenceData" : false
      },
      {
        "__metadata" : {
          "id" : "https://DEVSAPHRAPP01.ips.gov.il:4300/sap/opu/odata/sap/Z_PRESENCE_SRV/GetReasonsSet('00102236')",
          "uri" : "https://DEVSAPHRAPP01.ips.gov.il:4300/sap/opu/odata/sap/Z_PRESENCE_SRV/GetReasonsSet('00102236')",
          "type" : "Z_PRESENCE_SRV.GetReasons"
        },
        "ReportHours" : false,
        "IvCaller" : "",
        "ReportFullDays" : false,
        "IvUserName" : "",
        "CompleteDay" : false,
        "IvPersonnelNumber" : "00000000",
        "IvDate" : null,
        "IvPossiblePeriodReport" : "",
        "Pernr" : "00102236",
        "Date" : "\/Date(1779148800000)\/",
        "Code" : "0011",
        "TextCode" : "בתפקיד",
        "TimeInfty" : "2011",
        "PeriodReport" : false,
        "ManagerApprove" : false,
        "AdministratorApprove" : false,
        "AddFile" : false,
        "ReportComment" : false,
        "AdditionalAbsenceData" : false
      },
      {
        "__metadata" : {
          "id" : "https://DEVSAPHRAPP01.ips.gov.il:4300/sap/opu/odata/sap/Z_PRESENCE_SRV/GetReasonsSet('00102236')",
          "uri" : "https://DEVSAPHRAPP01.ips.gov.il:4300/sap/opu/odata/sap/Z_PRESENCE_SRV/GetReasonsSet('00102236')",
          "type" : "Z_PRESENCE_SRV.GetReasons"
        },
        "ReportHours" : false,
        "IvCaller" : "",
        "ReportFullDays" : false,
        "IvUserName" : "",
        "CompleteDay" : false,
        "IvPersonnelNumber" : "00000000",
        "IvDate" : null,
        "IvPossiblePeriodReport" : "",
        "Pernr" : "00102236",
        "Date" : "\/Date(1779148800000)\/",
        "Code" : "0012",
        "TextCode" : "ביהמ\"ש",
        "TimeInfty" : "2011",
        "PeriodReport" : false,
        "ManagerApprove" : false,
        "AdministratorApprove" : false,
        "AddFile" : false,
        "ReportComment" : false,
        "AdditionalAbsenceData" : false
      },
      {
        "__metadata" : {
          "id" : "https://DEVSAPHRAPP01.ips.gov.il:4300/sap/opu/odata/sap/Z_PRESENCE_SRV/GetReasonsSet('00102236')",
          "uri" : "https://DEVSAPHRAPP01.ips.gov.il:4300/sap/opu/odata/sap/Z_PRESENCE_SRV/GetReasonsSet('00102236')",
          "type" : "Z_PRESENCE_SRV.GetReasons"
        },
        "ReportHours" : false,
        "IvCaller" : "",
        "ReportFullDays" : false,
        "IvUserName" : "",
        "CompleteDay" : false,
        "IvPersonnelNumber" : "00000000",
        "IvDate" : null,
        "IvPossiblePeriodReport" : "",
        "Pernr" : "00102236",
        "Date" : "\/Date(1779148800000)\/",
        "Code" : "0013",
        "TextCode" : "הדרכת שב\"ס",
        "TimeInfty" : "2011",
        "PeriodReport" : false,
        "ManagerApprove" : false,
        "AdministratorApprove" : false,
        "AddFile" : false,
        "ReportComment" : false,
        "AdditionalAbsenceData" : false
      },
      {
        "__metadata" : {
          "id" : "https://DEVSAPHRAPP01.ips.gov.il:4300/sap/opu/odata/sap/Z_PRESENCE_SRV/GetReasonsSet('00102236')",
          "uri" : "https://DEVSAPHRAPP01.ips.gov.il:4300/sap/opu/odata/sap/Z_PRESENCE_SRV/GetReasonsSet('00102236')",
          "type" : "Z_PRESENCE_SRV.GetReasons"
        },
        "ReportHours" : false,
        "IvCaller" : "",
        "ReportFullDays" : false,
        "IvUserName" : "",
        "CompleteDay" : false,
        "IvPersonnelNumber" : "00000000",
        "IvDate" : null,
        "IvPossiblePeriodReport" : "",
        "Pernr" : "00102236",
        "Date" : "\/Date(1779148800000)\/",
        "Code" : "0014",
        "TextCode" : "עבודה מחוץ למשרד",
        "TimeInfty" : "2011",
        "PeriodReport" : false,
        "ManagerApprove" : false,
        "AdministratorApprove" : false,
        "AddFile" : false,
        "ReportComment" : false,
        "AdditionalAbsenceData" : false
      },
      {
        "__metadata" : {
          "id" : "https://DEVSAPHRAPP01.ips.gov.il:4300/sap/opu/odata/sap/Z_PRESENCE_SRV/GetReasonsSet('00102236')",
          "uri" : "https://DEVSAPHRAPP01.ips.gov.il:4300/sap/opu/odata/sap/Z_PRESENCE_SRV/GetReasonsSet('00102236')",
          "type" : "Z_PRESENCE_SRV.GetReasons"
        },
        "ReportHours" : false,
        "IvCaller" : "",
        "ReportFullDays" : false,
        "IvUserName" : "",
        "CompleteDay" : false,
        "IvPersonnelNumber" : "00000000",
        "IvDate" : null,
        "IvPossiblePeriodReport" : "",
        "Pernr" : "00102236",
        "Date" : "\/Date(1779148800000)\/",
        "Code" : "0015",
        "TextCode" : "עבודה מהבית",
        "TimeInfty" : "2011",
        "PeriodReport" : false,
        "ManagerApprove" : false,
        "AdministratorApprove" : false,
        "AddFile" : false,
        "ReportComment" : false,
        "AdditionalAbsenceData" : false
      },
      {
        "__metadata" : {
          "id" : "https://DEVSAPHRAPP01.ips.gov.il:4300/sap/opu/odata/sap/Z_PRESENCE_SRV/GetReasonsSet('00102236')",
          "uri" : "https://DEVSAPHRAPP01.ips.gov.il:4300/sap/opu/odata/sap/Z_PRESENCE_SRV/GetReasonsSet('00102236')",
          "type" : "Z_PRESENCE_SRV.GetReasons"
        },
        "ReportHours" : false,
        "IvCaller" : "",
        "ReportFullDays" : false,
        "IvUserName" : "",
        "CompleteDay" : false,
        "IvPersonnelNumber" : "00000000",
        "IvDate" : null,
        "IvPossiblePeriodReport" : "",
        "Pernr" : "00102236",
        "Date" : "\/Date(1779148800000)\/",
        "Code" : "0016",
        "TextCode" : "שעות נסיעה",
        "TimeInfty" : "2011",
        "PeriodReport" : false,
        "ManagerApprove" : false,
        "AdministratorApprove" : false,
        "AddFile" : false,
        "ReportComment" : false,
        "AdditionalAbsenceData" : false
      },
      {
        "__metadata" : {
          "id" : "https://DEVSAPHRAPP01.ips.gov.il:4300/sap/opu/odata/sap/Z_PRESENCE_SRV/GetReasonsSet('00102236')",
          "uri" : "https://DEVSAPHRAPP01.ips.gov.il:4300/sap/opu/odata/sap/Z_PRESENCE_SRV/GetReasonsSet('00102236')",
          "type" : "Z_PRESENCE_SRV.GetReasons"
        },
        "ReportHours" : false,
        "IvCaller" : "",
        "ReportFullDays" : false,
        "IvUserName" : "",
        "CompleteDay" : false,
        "IvPersonnelNumber" : "00000000",
        "IvDate" : null,
        "IvPossiblePeriodReport" : "",
        "Pernr" : "00102236",
        "Date" : "\/Date(1779148800000)\/",
        "Code" : "0018",
        "TextCode" : "משמרת תלם",
        "TimeInfty" : "2011",
        "PeriodReport" : false,
        "ManagerApprove" : false,
        "AdministratorApprove" : false,
        "AddFile" : false,
        "ReportComment" : false,
        "AdditionalAbsenceData" : false
      },
      {
        "__metadata" : {
          "id" : "https://DEVSAPHRAPP01.ips.gov.il:4300/sap/opu/odata/sap/Z_PRESENCE_SRV/GetReasonsSet('00102236')",
          "uri" : "https://DEVSAPHRAPP01.ips.gov.il:4300/sap/opu/odata/sap/Z_PRESENCE_SRV/GetReasonsSet('00102236')",
          "type" : "Z_PRESENCE_SRV.GetReasons"
        },
        "ReportHours" : false,
        "IvCaller" : "",
        "ReportFullDays" : false,
        "IvUserName" : "",
        "CompleteDay" : false,
        "IvPersonnelNumber" : "00000000",
        "IvDate" : null,
        "IvPossiblePeriodReport" : "",
        "Pernr" : "00102236",
        "Date" : "\/Date(1779148800000)\/",
        "Code" : "0050",
        "TextCode" : "אובדן תג",
        "TimeInfty" : "9011",
        "PeriodReport" : false,
        "ManagerApprove" : false,
        "AdministratorApprove" : false,
        "AddFile" : false,
        "ReportComment" : false,
        "AdditionalAbsenceData" : false
      },
      {
        "__metadata" : {
          "id" : "https://DEVSAPHRAPP01.ips.gov.il:4300/sap/opu/odata/sap/Z_PRESENCE_SRV/GetReasonsSet('00102236')",
          "uri" : "https://DEVSAPHRAPP01.ips.gov.il:4300/sap/opu/odata/sap/Z_PRESENCE_SRV/GetReasonsSet('00102236')",
          "type" : "Z_PRESENCE_SRV.GetReasons"
        },
        "ReportHours" : false,
        "IvCaller" : "",
        "ReportFullDays" : false,
        "IvUserName" : "",
        "CompleteDay" : false,
        "IvPersonnelNumber" : "00000000",
        "IvDate" : null,
        "IvPossiblePeriodReport" : "",
        "Pernr" : "00102236",
        "Date" : "\/Date(1779148800000)\/",
        "Code" : "0051",
        "TextCode" : "שכחתי להדפיס",
        "TimeInfty" : "9011",
        "PeriodReport" : false,
        "ManagerApprove" : false,
        "AdministratorApprove" : false,
        "AddFile" : false,
        "ReportComment" : false,
        "AdditionalAbsenceData" : false
      },
      {
        "__metadata" : {
          "id" : "https://DEVSAPHRAPP01.ips.gov.il:4300/sap/opu/odata/sap/Z_PRESENCE_SRV/GetReasonsSet('00102236')",
          "uri" : "https://DEVSAPHRAPP01.ips.gov.il:4300/sap/opu/odata/sap/Z_PRESENCE_SRV/GetReasonsSet('00102236')",
          "type" : "Z_PRESENCE_SRV.GetReasons"
        },
        "ReportHours" : false,
        "IvCaller" : "",
        "ReportFullDays" : false,
        "IvUserName" : "",
        "CompleteDay" : false,
        "IvPersonnelNumber" : "00000000",
        "IvDate" : null,
        "IvPossiblePeriodReport" : "",
        "Pernr" : "00102236",
        "Date" : "\/Date(1779148800000)\/",
        "Code" : "0052",
        "TextCode" : "בעיות תקשורת",
        "TimeInfty" : "9011",
        "PeriodReport" : false,
        "ManagerApprove" : false,
        "AdministratorApprove" : false,
        "AddFile" : false,
        "ReportComment" : false,
        "AdditionalAbsenceData" : false
      },
      {
        "__metadata" : {
          "id" : "https://DEVSAPHRAPP01.ips.gov.il:4300/sap/opu/odata/sap/Z_PRESENCE_SRV/GetReasonsSet('00102236')",
          "uri" : "https://DEVSAPHRAPP01.ips.gov.il:4300/sap/opu/odata/sap/Z_PRESENCE_SRV/GetReasonsSet('00102236')",
          "type" : "Z_PRESENCE_SRV.GetReasons"
        },
        "ReportHours" : false,
        "IvCaller" : "",
        "ReportFullDays" : false,
        "IvUserName" : "",
        "CompleteDay" : false,
        "IvPersonnelNumber" : "00000000",
        "IvDate" : null,
        "IvPossiblePeriodReport" : "",
        "Pernr" : "00102236",
        "Date" : "\/Date(1779148800000)\/",
        "Code" : "0053",
        "TextCode" : "הפסקת חשמל",
        "TimeInfty" : "9011",
        "PeriodReport" : false,
        "ManagerApprove" : false,
        "AdministratorApprove" : false,
        "AddFile" : false,
        "ReportComment" : false,
        "AdditionalAbsenceData" : false
      },
      {
        "__metadata" : {
          "id" : "https://DEVSAPHRAPP01.ips.gov.il:4300/sap/opu/odata/sap/Z_PRESENCE_SRV/GetReasonsSet('00102236')",
          "uri" : "https://DEVSAPHRAPP01.ips.gov.il:4300/sap/opu/odata/sap/Z_PRESENCE_SRV/GetReasonsSet('00102236')",
          "type" : "Z_PRESENCE_SRV.GetReasons"
        },
        "ReportHours" : false,
        "IvCaller" : "",
        "ReportFullDays" : false,
        "IvUserName" : "",
        "CompleteDay" : false,
        "IvPersonnelNumber" : "00000000",
        "IvDate" : null,
        "IvPossiblePeriodReport" : "",
        "Pernr" : "00102236",
        "Date" : "\/Date(1779148800000)\/",
        "Code" : "0054",
        "TextCode" : "תיקון דיווח",
        "TimeInfty" : "9011",
        "PeriodReport" : false,
        "ManagerApprove" : false,
        "AdministratorApprove" : false,
        "AddFile" : false,
        "ReportComment" : false,
        "AdditionalAbsenceData" : false
      },
      {
        "__metadata" : {
          "id" : "https://DEVSAPHRAPP01.ips.gov.il:4300/sap/opu/odata/sap/Z_PRESENCE_SRV/GetReasonsSet('00102236')",
          "uri" : "https://DEVSAPHRAPP01.ips.gov.il:4300/sap/opu/odata/sap/Z_PRESENCE_SRV/GetReasonsSet('00102236')",
          "type" : "Z_PRESENCE_SRV.GetReasons"
        },
        "ReportHours" : false,
        "IvCaller" : "",
        "ReportFullDays" : false,
        "IvUserName" : "",
        "CompleteDay" : false,
        "IvPersonnelNumber" : "00000000",
        "IvDate" : null,
        "IvPossiblePeriodReport" : "",
        "Pernr" : "00102236",
        "Date" : "\/Date(1779148800000)\/",
        "Code" : "0055",
        "TextCode" : "אחר",
        "TimeInfty" : "9011",
        "PeriodReport" : false,
        "ManagerApprove" : false,
        "AdministratorApprove" : false,
        "AddFile" : false,
        "ReportComment" : false,
        "AdditionalAbsenceData" : false
      }
    ]
  }
}